{
  "entrypoints": {
    "js/app": {
      "js": [
        "/build/runtime.8132cb27.js",
        "/build/560.e2a77bcc.js",
        "/build/js/app.e8f39cdd.js"
      ],
      "css": [
        "/build/js/app.f1220f5a.css"
      ]
    },
    "css/email": {
      "js": [
        "/build/runtime.8132cb27.js"
      ],
      "css": [
        "/build/css/email.5c048648.css"
      ]
    },
    "css/editmode": {
      "js": [
        "/build/runtime.8132cb27.js"
      ],
      "css": [
        "/build/css/editmode.31d6cfe0.css"
      ]
    }
  }
}